src/barrel_shifter.v
module barrel_shifter(data_in,shift_amt,dir,data_out);
input [31:0] data_in;
input [4:0] shift_amt;
input dir;
output [31:0] data_out;
assign data_out=(dir==1'b0)?(data_in<<shift_amt):(data_in>>shift_amt);
endmodule

tb_barrel_shifter.v
`timescale 1ns / 1ps

module tb_barrel_shifter;

    reg [31:0] data_in;
    reg [4:0] shift_amt;
    reg dir;
    wire [31:0] data_out;

    
    barrel_shifter uut (data_in, shift_amt, dir, data_out);
    initial begin
        $dumpfile("barrel_shifter_project.vcd");
        $dumpvars(0, tb_barrel_shifter);

        data_in = 32'b00000000000000000000000000001111; shift_amt = 5'd0; dir = 1'b0; #10;
        data_in = 32'b00000000000000000000000000001111; shift_amt = 5'd1; dir = 1'b0; #10;
        data_in = 32'b00000000000000000000000000001111; shift_amt = 5'd2; dir = 1'b0; #10;
        data_in = 32'b00000000000000000000000000001111; shift_amt = 5'd3; dir = 1'b1; #10;
        data_in = 32'b00000000000000000000000000001111; shift_amt = 5'd4; dir = 1'b1; #10;
        data_in = 32'b00000000000000000000000000001111; shift_amt = 5'd5; dir = 1'b0; #10;
        data_in = 32'b00000000000000000000000000001111; shift_amt = 5'd6; dir = 1'b1; #10;
        data_in = 32'b00000000000000000000000000001111; shift_amt = 5'd0; dir = 1'b0; #10;

        $finish;
    end

    
    initial begin
        $monitor("Time=%0t | data_in=%b | shift_amt=%d | dir=%b | data_out=%b",
                 $time, data_in, shift_amt, dir, data_out);
    end

endmodule

barrel_shifter_project.vcd
$date
	Wed Jun 18 10:31:07 2025
$end
$version
	Icarus Verilog
$end
$timescale
	1ps
$end
$scope module tb_barrel_shifter $end
$var wire 32 ! data_out [31:0] $end
$var reg 32 " data_in [31:0] $end
$var reg 1 # dir $end
$var reg 5 $ shift_amt [4:0] $end
$scope module uut $end
$var wire 32 % data_in [31:0] $end
$var wire 1 # dir $end
$var wire 5 & shift_amt [4:0] $end
$var wire 32 ' data_out [31:0] $end
$upscope $end
$upscope $end
$enddefinitions $end
$comment Show the parameter values. $end
$dumpall
$end
#0
$dumpvars
b1111 '
b0 &
b1111 %
b0 $
0#
b1111 "
b1111 !
$end
#10000
b11110 !
b11110 '
b1 $
b1 &
#20000
b111100 !
b111100 '
b10 $
b10 &
#30000
b1 !
b1 '
1#
b11 $
b11 &
#40000
b0 !
b0 '
b100 $
b100 &
#50000
b111100000 !
b111100000 '
0#
b101 $
b101 &
#60000
b0 !
b0 '
1#
b110 $
b110 &
#70000
b1111 !
b1111 '
0#
b0 $
b0 &
